{
  "instagram_url": "https://www.instagram.com/ripplinghq/",
  "twitter_url": "https://x.com/rippling",
  "positions": [
    {
      "country": "USA",
      "city": "New York",
      "postal_code": "NY 10007",
      "address": "4 World Trade Center, 150 Greenwich St 59th floor",
      "map": "{\"type\":\"Point\",\"coordinates\":[-74.0123529,40.7103023]}"
    },
    {
      "country": "United Kingdom",
      "city": "London",
      "postal_code": " W1T 1RR",
      "address": "33 Charlotte St., 2nd Floor, ",
      "map": "{\"type\":\"Point\",\"coordinates\":[-0.1356178,51.5189552]}"
    },
    {
      "country": "India",
      "city": "Bellandur, Bengaluru",
      "postal_code": "Karnataka 560103",
      "address": "Block G&H, Tulip), 6th, EMBASSY TECH VILLAGE, Outer Ring Rd, Devarabisanahalli",
      "map": "{\"type\":\"Point\",\"coordinates\":[77.6917876,12.928778]}"
    }
  ],
  "job_board_provider": "rippling",
  "company_url": "https://www.rippling.com",
  "job_board_hostname": "rippling",
  "linkedin_url": "https://www.linkedin.com/company/rippling",
  "youtube_url": "https://www.youtube.com/@RipplingHQ",
  "github_url": "https://github.com/rippling",
  "job_board_url": "https://www.rippling.com/careers",
  "facebook_url": "https://www.facebook.com/ripplingapp/",
  "title": "Rippling",
  "tags": [
    "hr",
    "ats"
  ],
  "description": "Rippling is the workforce management platform that eliminates the friction from running a business. With Rippling, all your data related to people, processes, and systems is in one place. It flows directly into Rippling’s business applications, giving every team a shared source of truth, the power to automate tasks, and access to the insights they need, so you can accelerate business execution and run more efficiently."
}
