{
    "title": "SOLYTIC",
    "description": "#startup #solar #energy-transformation",
    "tags": [
        "startup",
        "solar",
        "energy-transformation"
    ],
    "job_board_url": "https://solytic.jobs.personio.de/",
    "job_board_provider": "personio",
    "job_board_hostname": "solytic",
    "positions": [
        {
            "country": "germany",
            "city": "berlin",
            "map": {
                "type": "Point",
                "coordinates": [
                    13.382398,
                    52.530681
                ]
            }
        }
    ]
}