{
  "twitter_url": "https://twitter.com/rocketlab",
  "wikipedia_url": "https://en.wikipedia.org/wiki/Rocket_Lab",
  "job_board_provider": "greenhouse",
  "company_url": "https://www.rocketlabusa.com",
  "job_board_hostname": "rocketlab",
  "linkedin_url": "https://www.linkedin.com/company/rocket-lab-limited",
  "youtube_url": "https://www.youtube.com/user/RocketLabNZ",
  "job_board_url": "https://www.rocketlabusa.com/careers",
  "facebook_url": "https://www.facebook.com/RocketLabUSA/",
  "title": "Rocket Lab",
  "tags": [
    "space",
    "rockets"
  ],
  "description": "Rocket Lab is a global leader in launch and space systems. The rockets and satellites we build and launch enable some of the most ambitious and vital space missions globally, supporting scientific exploration, Earth observation and missions to combat climate change, national security, and exciting new technology demonstrations. Our Electron rocket has provided reliable access to orbit since 2018, becoming one of the most frequently launched rockets in the world."
}
