{
    "title": "Mercari",
    "company_url": "https://mercari.com",
    "job_board_url": "https://careers.mercari.com",
    "job_board_provider": "workable",
    "job_board_hostname": "mercari",
    "description": "Mercari is a Japan-based company with the mission of “create value in a global marketplace where anyone can buy & sell.” Having continuously worked toward this goal since our founding in 2013, we are now transforming from a startup into a global player.",
    "tags": [
        "marketplace",
        "startup",
        "unicorn"
    ],
    "twitter_url": "https://twitter.com/mercari_team",
    "linkedin_url": "https://www.linkedin.com/company/mercari-inc-",
    "instagram_url": "https://www.instagram.com/mercari_life",
    "facebook_url": "https://www.facebook.com/mercanteam1"
}